dastro_bot/__init__.py
dastro_bot/attachments_downloader.py
dastro_bot/bot.py
dastro_bot/install.py
dastro_bot-1.3.5.dist-info/LICENSE
dastro_bot-1.3.5.dist-info/METADATA
dastro_bot-1.3.5.dist-info/WHEEL
dastro_bot-1.3.5.dist-info/top_level.txt
dastro_bot-1.3.5.dist-info/RECORD
