Metadata-Version: 2.1
Name: dastro-bot
Version: 1.3.5
Summary: Discord bot for Star Citizen players
Home-page: https://github.com/Mirdalan/discord_astro_bot
Author: Michal Chrzanowski
Author-email: michrzan@gmail.com
License: MIT
Keywords: star citizen discord bot
Platform: UNKNOWN
Classifier: Development Status :: 4 - Beta
Classifier: Intended Audience :: Developers
Classifier: Topic :: Games/Entertainment
Classifier: License :: OSI Approved :: MIT License
Classifier: Programming Language :: Python :: 3.5
Classifier: Programming Language :: Python :: 3.6
Requires-Python: ~=3.5
Requires-Dist: aiohttp (==3.4.4)
Requires-Dist: async-timeout (==3.0.1)
Requires-Dist: base-astro-bot (>=1.3.0)
Requires-Dist: disco-py (==0.0.12)
Requires-Dist: websocket-client (==0.44.0) ; "linux" in sys_platform
Requires-Dist: gevent (==1.2.2) ; python_version<"3.7"
Requires-Dist: gevent (>=1.3.6) ; python_version>="3.7"
Requires-Dist: websocket-client (==0.46.0) ; sys_platform == "win32"
